com_chery/chery_user_util/__init__.py
com_chery/chery_user_util/pom.py
com_chery/chery_user_util/user_util.py
com_chery_user_util-0.0.6.dist-info/METADATA
com_chery_user_util-0.0.6.dist-info/WHEEL
com_chery_user_util-0.0.6.dist-info/top_level.txt
com_chery_user_util-0.0.6.dist-info/RECORD
